{
  "parent": "minecraft:recipes/root",
  "criteria": {
    "has_bit": {
      "conditions": {
        "items": [
          {
            "items": "minecraft:bit"
          }
        ]
      },
      "trigger": "minecraft:inventory_changed"
    },
    "has_the_recipe": {
      "conditions": {
        "recipe": "aprils-legacy:left_curly"
      },
      "trigger": "minecraft:recipe_unlocked"
    }
  },
  "requirements": [
    [
      "has_the_recipe",
      "has_bit"
    ]
  ],
  "rewards": {
    "recipes": [
      "aprils-legacy:left_curly"
    ]
  }
}